README.md
setup.py
mysecondvenv/__init__.py
mysecondvenv/polynom.py
mysecondvenv/test_polynom.py
mysecondvenv.egg-info/PKG-INFO
mysecondvenv.egg-info/SOURCES.txt
mysecondvenv.egg-info/dependency_links.txt
mysecondvenv.egg-info/top_level.txt