Metadata-Version: 1.1
Name: mysecondvenv
Version: 0.0.2
Summary: my second PypI package
Home-page: UNKNOWN
Author: Antoine Marullaz
Author-email: antoine.marullaz@gmail.com
License: WTFPL
Keywords: example documentation tutorial
Platform: UNKNOWN
Classifier: Programming Language :: Python
Classifier: Development Status :: 1 - Planning
Classifier: License :: OSI Approved
Classifier: Natural Language :: French
Classifier: Operating System :: OS Independent
Classifier: Programming Language :: Python :: 2.7
Classifier: Topic :: Communications
